[
  {
    "id": "dq_749c81eb_1",
    "type": "multiple",
    "content": "以下哪些方法可以用于字符串？",
    "options": [
      "upper()",
      "lower()",
      "append()",
      "sort()"
    ],
    "correct_answer": [
      "upper()",
      "lower()"
    ],
    "explanation": "upper() 和 lower() 是字符串方法，append() 和 sort() 是列表方法。",
    "knowledge_point_id": "1.4",
    "knowledge_point_name": "字符串处理"
  },
  {
    "id": "dq_749c81eb_2",
    "type": "single",
    "content": "字符串的 count() 方法的作用是什么？",
    "options": [
      "获取长度",
      "计算子字符串出现次数",
      "查找位置",
      "替换字符"
    ],
    "correct_answer": "计算子字符串出现次数",
    "explanation": "count() 返回子字符串在字符串中出现的次数。",
    "knowledge_point_id": "1.4",
    "knowledge_point_name": "字符串处理"
  },
  {
    "id": "dq_749c81eb_3",
    "type": "single",
    "content": "close() 方法的作用是什么？",
    "options": [
      "打开文件",
      "读取文件",
      "关闭文件",
      "删除文件"
    ],
    "correct_answer": "关闭文件",
    "explanation": "close() 方法关闭文件，释放资源。",
    "knowledge_point_id": "5.1",
    "knowledge_point_name": "文件操作"
  },
  {
    "id": "dq_749c81eb_4",
    "type": "single",
    "content": "文件打开模式 \"a\" 表示什么？",
    "options": [
      "读取",
      "写入",
      "追加",
      "二进制"
    ],
    "correct_answer": "追加",
    "explanation": "\"a\" 模式表示以追加模式打开文件，在末尾添加内容。",
    "knowledge_point_id": "5.1",
    "knowledge_point_name": "文件操作"
  }
]